pyqsys/__init__.py
pyqsys/qrc_methods.py
pyqsys/qsc_core.py
pyqsys-0.0.2.dist-info/LICENSE
pyqsys-0.0.2.dist-info/METADATA
pyqsys-0.0.2.dist-info/NOTICE
pyqsys-0.0.2.dist-info/WHEEL
pyqsys-0.0.2.dist-info/top_level.txt
pyqsys-0.0.2.dist-info/RECORD
