Metadata-Version: 2.1
Name: pyqsys
Version: 0.0.2
Summary: An attempt to create a Python library to communicate with QSYS Cores via their QRC (JSONRPC 2.0) protocol.
Author-email: Maximilian Schöberl <maxschoeberl@gmail.com>
Project-URL: Homepage, https://github.com/mexxs/pyqsys
Project-URL: Bug Tracker, https://github.com/mexxs/pyqsys/issues
Classifier: Programming Language :: Python :: 3
Classifier: License :: OSI Approved :: MIT License
Classifier: Operating System :: OS Independent
Requires-Python: >=3.7
License-File: LICENSE
License-File: NOTICE
